[{"topic_id": "1", "topic_name": "Понимание основного содержания прослушанного текста", "categories": [{"category_id": "27", "category_name": "Задания для подготовки"}, {"category_id": "57", "category_name": "Задания на основе экзаменов прошлых лет"}]}, {"topic_id": "2", "topic_name": "Выделение информации в прослушанном тексте", "categories": [{"category_id": "58", "category_name": "Задания на основе экзаменов прошлых лет"}, {"category_id": "47", "category_name": "Задания для подготовки"}]}, {"topic_id": "3", "topic_name": "Полное понимание устной речи: интервью", "categories": [{"category_id": "59", "category_name": "Задания на основе экзаменов прошлых лет"}, {"category_id": "8", "category_name": "Задания для подготовки"}]}, {"topic_id": "4", "topic_name": "Полное понимание устной речи: интервью", "categories": [{"category_id": "60", "category_name": "Задания на основе экзаменов прошлых лет"}, {"category_id": "9", "category_name": "Задания для подготовки"}]}, {"topic_id": "5", "topic_name": "Полное понимание устной речи: интервью", "categories": [{"category_id": "61", "category_name": "Задания на основе экзаменов прошлых лет"}, {"category_id": "10", "category_name": "Задания для подготовки"}]}, {"topic_id": "6", "topic_name": "Полное понимание устной речи: интервью", "categories": [{"category_id": "62", "category_name": "Задания на основе экзаменов прошлых лет"}, {"category_id": "11", "category_name": "Задания для подготовки"}]}, {"topic_id": "7", "topic_name": "Полное понимание устной речи: интервью", "categories": [{"category_id": "63", "category_name": "Задания на основе экзаменов прошлых лет"}, {"category_id": "43", "category_name": "Задания для подготовки"}]}, {"topic_id": "8", "topic_name": "Полное понимание устной речи: интервью", "categories": [{"category_id": "64", "category_name": "Задания на основе экзаменов прошлых лет"}, {"category_id": "44", "category_name": "Задания для подготовки"}]}, {"topic_id": "9", "topic_name": "Полное понимание устной речи: интервью", "categories": [{"category_id": "65", "category_name": "Задания на основе экзаменов прошлых лет"}, {"category_id": "12", "category_name": "Задания для подготовки"}]}, {"topic_id": "10", "topic_name": "Понимание основного содержания текста", "categories": [{"category_id": "66", "category_name": "Задания на основе экзаменов прошлых лет"}, {"category_id": "28", "category_name": "Задания для подготовки"}]}, {"topic_id": "11", "topic_name": "Понимание структурно-смысловых связей в тексте", "categories": [{"category_id": "67", "category_name": "Задания на основе экзаменов прошлых лет"}, {"category_id": "29", "category_name": "Задания для подготовки"}]}, {"topic_id": "12", "topic_name": "Полное понимание информации в тексте", "categories": [{"category_id": "68", "category_name": "Задания на основе экзаменов прошлых лет"}, {"category_id": "13", "category_name": "Задания для подготовки"}]}, {"topic_id": "13", "topic_name": "Полное понимание информации в тексте", "categories": [{"category_id": "69", "category_name": "Задания на основе экзаменов прошлых лет"}, {"category_id": "14", "category_name": "Задания для подготовки"}]}, {"topic_id": "14", "topic_name": "Полное понимание информации в тексте", "categories": [{"category_id": "70", "category_name": "Задания на основе экзаменов прошлых лет"}, {"category_id": "15", "category_name": "Задания для подготовки"}]}, {"topic_id": "15", "topic_name": "Полное понимание информации в тексте", "categories": [{"category_id": "71", "category_name": "Задания на основе экзаменов прошлых лет"}, {"category_id": "16", "category_name": "Задания для подготовки"}]}, {"topic_id": "16", "topic_name": "Полное понимание информации в тексте", "categories": [{"category_id": "72", "category_name": "Задания на основе экзаменов прошлых лет"}, {"category_id": "17", "category_name": "Задания для подготовки"}]}, {"topic_id": "17", "topic_name": "Полное понимание информации в тексте", "categories": [{"category_id": "73", "category_name": "Задания на основе экзаменов прошлых лет"}, {"category_id": "18", "category_name": "Задания для подготовки"}]}, {"topic_id": "18", "topic_name": "Полное понимание информации в тексте", "categories": [{"category_id": "74", "category_name": "Задания на основе экзаменов прошлых лет"}, {"category_id": "19", "category_name": "Задания для подготовки"}]}, {"topic_id": "19", "topic_name": "Грамматические навыки", "categories": [{"category_id": "75", "category_name": "Задания на основе экзаменов прошлых лет"}, {"category_id": "30", "category_name": "Задания для подготовки"}]}, {"topic_id": "20", "topic_name": "Грамматические навыки", "categories": [{"category_id": "76", "category_name": "Задания на основе экзаменов прошлых лет"}, {"category_id": "31", "category_name": "Задания для подготовки"}]}, {"topic_id": "21", "topic_name": "Грамматические навыки", "categories": [{"category_id": "77", "category_name": "Задания на основе экзаменов прошлых лет"}, {"category_id": "32", "category_name": "Задания для подготовки"}]}, {"topic_id": "22", "topic_name": "Грамматические навыки", "categories": [{"category_id": "78", "category_name": "Задания на основе экзаменов прошлых лет"}, {"category_id": "33", "category_name": "Задания для подготовки"}]}, {"topic_id": "23", "topic_name": "Грамматические навыки", "categories": [{"category_id": "79", "category_name": "Задания на основе экзаменов прошлых лет"}, {"category_id": "34", "category_name": "Задания для подготовки"}]}, {"topic_id": "24", "topic_name": "Грамматические навыки", "categories": [{"category_id": "80", "category_name": "Задания на основе экзаменов прошлых лет"}, {"category_id": "35", "category_name": "Задания для подготовки"}]}, {"topic_id": "25", "topic_name": "Лексико-грамматические навыки", "categories": [{"category_id": "81", "category_name": "Задания на основе экзаменов прошлых лет"}, {"category_id": "37", "category_name": "Задания для подготовки"}]}, {"topic_id": "26", "topic_name": "Лексико-грамматические навыки", "categories": [{"category_id": "82", "category_name": "Задания на основе экзаменов прошлых лет"}, {"category_id": "38", "category_name": "Задания для подготовки"}]}, {"topic_id": "27", "topic_name": "Лексико-грамматические навыки", "categories": [{"category_id": "83", "category_name": "Задания на основе экзаменов прошлых лет"}, {"category_id": "39", "category_name": "Задания для подготовки"}]}, {"topic_id": "28", "topic_name": "Лексико-грамматические навыки", "categories": [{"category_id": "84", "category_name": "Задания на основе экзаменов прошлых лет"}, {"category_id": "40", "category_name": "Задания для подготовки"}]}, {"topic_id": "29", "topic_name": "Лексико-грамматические навыки", "categories": [{"category_id": "85", "category_name": "Задания на основе экзаменов прошлых лет"}, {"category_id": "41", "category_name": "Задания для подготовки"}]}, {"topic_id": "30", "topic_name": "Лексико-грамматические навыки", "categories": [{"category_id": "86", "category_name": "Задания на основе экзаменов прошлых лет"}, {"category_id": "20", "category_name": "Задания для подготовки"}]}, {"topic_id": "31", "topic_name": "Лексико-грамматические навыки", "categories": [{"category_id": "87", "category_name": "Задания на основе экзаменов прошлых лет"}, {"category_id": "21", "category_name": "Задания для подготовки"}]}, {"topic_id": "32", "topic_name": "Лексико-грамматические навыки", "categories": [{"category_id": "88", "category_name": "Задания на основе экзаменов прошлых лет"}, {"category_id": "22", "category_name": "Задания для подготовки"}]}, {"topic_id": "33", "topic_name": "Лексико-грамматические навыки", "categories": [{"category_id": "89", "category_name": "Задания на основе экзаменов прошлых лет"}, {"category_id": "23", "category_name": "Задания для подготовки"}]}, {"topic_id": "34", "topic_name": "Лексико-грамматические навыки", "categories": [{"category_id": "90", "category_name": "Задания на основе экзаменов прошлых лет"}, {"category_id": "24", "category_name": "Задания для подготовки"}]}, {"topic_id": "35", "topic_name": "Лексико-грамматические навыки", "categories": [{"category_id": "91", "category_name": "Задания на основе экзаменов прошлых лет"}, {"category_id": "25", "category_name": "Задания для подготовки"}]}, {"topic_id": "36", "topic_name": "Лексико-грамматические навыки", "categories": [{"category_id": "92", "category_name": "Задания на основе экзаменов прошлых лет"}, {"category_id": "26", "category_name": "Задания для подготовки"}]}, {"topic_id": "37", "topic_name": "Электронное письмо личного характера", "categories": [{"category_id": "93", "category_name": "Задания на основе экзаменов прошлых лет"}, {"category_id": "52", "category_name": "Задания для подготовки"}]}, {"topic_id": "38", "topic_name": "Развернутое письменное высказывание по предложенной проблеме", "categories": [{"category_id": "94", "category_name": "Задания на основе экзаменов прошлых лет"}, {"category_id": "56", "category_name": "Задания для подготовки"}]}, {"topic_id": "39", "topic_name": "Чтение текста вслух", "categories": [{"category_id": "95", "category_name": "Задания на основе экзаменов прошлых лет"}, {"category_id": "48", "category_name": "Задания для подготовки"}]}, {"topic_id": "40", "topic_name": "Условный диалог-расспрос", "categories": [{"category_id": "96", "category_name": "Задания на основе экзаменов прошлых лет"}, {"category_id": "53", "category_name": "Задания для подготовки"}]}, {"topic_id": "41", "topic_name": "Монолог", "categories": [{"category_id": "97", "category_name": "Задания на основе экзаменов прошлых лет"}, {"category_id": "54", "category_name": "Задания для подготовки"}]}, {"topic_id": "42", "topic_name": "Монолог", "categories": [{"category_id": "98", "category_name": "Задания на основе экзаменов прошлых лет"}, {"category_id": "55", "category_name": "Задания для подготовки"}]}]